setup.py
salure_helpers/salureconnect/__init__.py
salure_helpers/salureconnect/files.py
salure_helpers/salureconnect/salureconnect.py
salure_helpers_salureconnect.egg-info/PKG-INFO
salure_helpers_salureconnect.egg-info/SOURCES.txt
salure_helpers_salureconnect.egg-info/dependency_links.txt
salure_helpers_salureconnect.egg-info/not-zip-safe
salure_helpers_salureconnect.egg-info/requires.txt
salure_helpers_salureconnect.egg-info/top_level.txt