Metadata-Version: 1.0
Name: salure-helpers-salureconnect
Version: 1.4.0
Summary: SalureConnect wrapper from Salure
Home-page: UNKNOWN
Author: D&A Salure
Author-email: support@salureconnnect.com
License: Salure License
Platform: UNKNOWN
